MANIFEST.in
README.md
setup.cfg
setup.py
src/SIIM2_Server.egg-info/PKG-INFO
src/SIIM2_Server.egg-info/SOURCES.txt
src/SIIM2_Server.egg-info/dependency_links.txt
src/SIIM2_Server.egg-info/requires.txt
src/SIIM2_Server.egg-info/top_level.txt
src/cid/__init__.py
src/cid/caliope_server.py
src/cid/model/SIIMModel.py
src/cid/model/__init__.py
src/cid/modules/__init__.py
src/cid/modules/core/__init__.py
src/cid/modules/core/dispatcher/__init__.py
src/cid/modules/core/dispatcher/router.py
src/cid/modules/core/file_uploader/__init__.py
src/cid/modules/core/file_uploader/uploader.py
src/cid/modules/core/jsonrpc/__init__.py
src/cid/modules/core/module_manager/__init__.py
src/cid/modules/core/module_manager/module_loader.py
src/cid/modules/core/server_notifications/__init__.py
src/cid/modules/core/server_notifications/views.py
src/cid/utils/__init__.py
src/cid/utils/fileUtils.py
src/cid/utils/helpers.py
src/test/__init__.py
src/test/siim_tests.py