Metadata-Version: 1.0
Name: SIIM2-Server
Version: 0.0.1
Summary: UNKNOWN
Home-page: https://proyectos.correlibre.org/caliope/caliope_server_el_cid
Author: Sebastián Ortiz Vásquez
Author-email: neoecos@gmail.com
License: GNU AFFERO GENERAL PUBLIC LICENSE
Platform: UNKNOWN
